README.md
setup.py
pykonkeio/__init__.py
pykonkeio/__main__.py
pykonkeio/error.py
pykonkeio/manager.py
pykonkeio/socket.py
pykonkeio/utils.py
pykonkeio.egg-info/PKG-INFO
pykonkeio.egg-info/SOURCES.txt
pykonkeio.egg-info/dependency_links.txt
pykonkeio.egg-info/entry_points.txt
pykonkeio.egg-info/requires.txt
pykonkeio.egg-info/top_level.txt
pykonkeio/device/__init__.py
pykonkeio/device/base.py
pykonkeio/device/basemul.py
pykonkeio/device/basetoggle.py
pykonkeio/device/k1.py
pykonkeio/device/k2.py
pykonkeio/device/kbulb.py
pykonkeio/device/klight.py
pykonkeio/device/micmul.py
pykonkeio/device/minik.py
pykonkeio/device/mul.py
pykonkeio/mixin/__init__.py
pykonkeio/mixin/ir.py
pykonkeio/mixin/rf.py