Metadata-Version: 2.1
Name: pykonkeio
Version: 2.1.7
Summary: Python library for interfacing with konke smart appliances
Home-page: https://github.com/jedmeng/python-konkeio
Author: jedmeng
Author-email: jedm@jedm.cn
License: GPLv3
Keywords: konke,iot
Platform: UNKNOWN
Classifier: Development Status :: 4 - Beta
Classifier: Programming Language :: Python :: 3
Classifier: License :: OSI Approved :: GNU Lesser General Public License v3 (LGPLv3)
Classifier: Operating System :: OS Independent
Requires-Python: >=3.5
